wheelhouse_uploader/__init__.py
wheelhouse_uploader/__main__.py
wheelhouse_uploader/cmd.py
wheelhouse_uploader/commandline.py
wheelhouse_uploader/fetch.py
wheelhouse_uploader/upload.py
wheelhouse_uploader/utils.py
wheelhouse_uploader-0.10.3.dist-info/LICENSE
wheelhouse_uploader-0.10.3.dist-info/METADATA
wheelhouse_uploader-0.10.3.dist-info/WHEEL
wheelhouse_uploader-0.10.3.dist-info/top_level.txt
wheelhouse_uploader-0.10.3.dist-info/RECORD
