Metadata-Version: 2.1
Name: wheelhouse-uploader
Version: 0.10.3
Summary: Upload wheels to any cloud storage supported by Libcloud
Home-page: http://github.com/ogrisel/wheelhouse-uploader
Maintainer: Olivier Grisel
Maintainer-email: olivier.grisel@ensta.org
License: MIT
Platform: UNKNOWN
Classifier: License :: OSI Approved
Classifier: Programming Language :: Python
Classifier: Topic :: Software Development
Classifier: Operating System :: Microsoft :: Windows
Classifier: Operating System :: POSIX
Classifier: Operating System :: Unix
Classifier: Operating System :: MacOS
Classifier: Programming Language :: Python :: 2
Classifier: Programming Language :: Python :: 2.7
Classifier: Programming Language :: Python :: 3
Classifier: Programming Language :: Python :: 3.5
Classifier: Programming Language :: Python :: 3.6
Classifier: Programming Language :: Python :: 3.7
Requires-Dist: setuptools (>=0.9)
Requires-Dist: packaging
Requires-Dist: certifi
Requires-Dist: apache-libcloud (==2.2.1)
Requires-Dist: futures ; python_version == "2.7"
